{
  "generated_at": "2026-02-25T00:12:07Z",
  "date": "2026-02-25",
  "sports": {
    "nba": {
      "status": "ok",
      "metrics": {
        "accuracy": 0.65,
        "logloss": 0.621,
        "brier": 0.2152
      },
      "picks": [
        {
          "home_team": "Chicago Bulls",
          "away_team": "Charlotte Hornets",
          "pick": "H",
          "pick_label": "Chicago Bulls",
          "p_win": 0.6961,
          "implied_odds": 1.44,
          "signal": "alta",
          "date": "2026-02-24",
          "model_spread": 12.1,
          "house_spread": null,
          "house_odds": null,
          "house_implied_pct": null,
          "edge_pct": null,
          "house_total": null,
          "injuries_home": [],
          "injuries_away": [],
          "note": "✅ 5-1 vs 3-4 — → Apostar ML Chicago Bulls (modelo 70%)"
        },
        {
          "home_team": "Milwaukee Bucks",
          "away_team": "Miami Heat",
          "pick": "H",
          "pick_label": "Milwaukee Bucks",
          "p_win": 0.6536,
          "implied_odds": 1.53,
          "signal": "media",
          "date": "2026-02-24",
          "model_spread": 9.3,
          "house_spread": null,
          "house_odds": null,
          "house_implied_pct": null,
          "edge_pct": null,
          "house_total": null,
          "injuries_home": [],
          "injuries_away": [],
          "note": "⚠️ 5-2 vs 3-3 — → Apostar ML Milwaukee Bucks (modelo 65%)"
        },
        {
          "home_team": "Los Angeles Lakers",
          "away_team": "Orlando Magic",
          "pick": "H",
          "pick_label": "Los Angeles Lakers",
          "p_win": 0.6103,
          "implied_odds": 1.64,
          "signal": "media",
          "date": "2026-02-24",
          "model_spread": 6.5,
          "house_spread": null,
          "house_odds": null,
          "house_implied_pct": null,
          "edge_pct": null,
          "house_total": null,
          "injuries_home": [],
          "injuries_away": [],
          "note": "⚠️ 5-2 vs 3-4 — → Apostar ML Los Angeles Lakers (modelo 61%)"
        }
      ],
      "name": "NBA",
      "analysis": ""
    },
    "nhl": {
      "status": "error",
      "reason": "Can only use .str accessor with string values, not floating",
      "picks": [],
      "name": "NHL"
    },
    "mlb": {
      "status": "skipped",
      "reason": "Fuera de temporada (Oct–Mar)",
      "picks": [],
      "name": "MLB"
    },
    "epl": {
      "status": "ok",
      "metrics": {
        "accuracy": 0.4545,
        "logloss": 1.0439,
        "brier": 0.2093
      },
      "picks": [],
      "name": "Premier League"
    },
    "laliga": {
      "status": "ok",
      "metrics": {
        "accuracy": 0.44,
        "logloss": 1.0338,
        "brier": 0.2076
      },
      "picks": [],
      "name": "La Liga"
    },
    "ligue1": {
      "status": "ok",
      "metrics": {
        "accuracy": 0.5714,
        "logloss": 0.9621,
        "brier": 0.1909
      },
      "picks": [],
      "name": "Ligue 1"
    },
    "bundesliga": {
      "status": "ok",
      "metrics": {
        "accuracy": 0.5714,
        "logloss": 0.9886,
        "brier": 0.1902
      },
      "picks": [],
      "name": "Bundesliga"
    },
    "primeira": {
      "status": "ok",
      "metrics": {
        "accuracy": 0.5238,
        "logloss": 0.9563,
        "brier": 0.1884
      },
      "picks": [],
      "name": "Primeira Liga"
    },
    "ucl": {
      "status": "ok",
      "metrics": {
        "accuracy": 0.5312,
        "logloss": 1.017,
        "brier": 0.2051
      },
      "picks": [],
      "name": "Champions League"
    }
  },
  "parlays": {
    "by_sport": {
      "nba": {
        "cuota_3": {
          "legs": [
            {
              "sport": "nba",
              "match": "Milwaukee Bucks vs Miami Heat",
              "pick": "Milwaukee Bucks",
              "p_win": 0.6536,
              "implied_odds": 1.53
            },
            {
              "sport": "nba",
              "match": "Los Angeles Lakers vs Orlando Magic",
              "pick": "Los Angeles Lakers",
              "p_win": 0.6103,
              "implied_odds": 1.64
            }
          ],
          "total_odds": 2.51,
          "combined_prob": 0.3989,
          "n_legs": 2
        },
        "cuota_4": {
          "legs": [
            {
              "sport": "nba",
              "match": "Chicago Bulls vs Charlotte Hornets",
              "pick": "Chicago Bulls",
              "p_win": 0.6961,
              "implied_odds": 1.44
            },
            {
              "sport": "nba",
              "match": "Milwaukee Bucks vs Miami Heat",
              "pick": "Milwaukee Bucks",
              "p_win": 0.6536,
              "implied_odds": 1.53
            },
            {
              "sport": "nba",
              "match": "Los Angeles Lakers vs Orlando Magic",
              "pick": "Los Angeles Lakers",
              "p_win": 0.6103,
              "implied_odds": 1.64
            }
          ],
          "total_odds": 3.61,
          "combined_prob": 0.2777,
          "n_legs": 3
        },
        "cuota_5": {
          "legs": [
            {
              "sport": "nba",
              "match": "Chicago Bulls vs Charlotte Hornets",
              "pick": "Chicago Bulls",
              "p_win": 0.6961,
              "implied_odds": 1.44
            },
            {
              "sport": "nba",
              "match": "Milwaukee Bucks vs Miami Heat",
              "pick": "Milwaukee Bucks",
              "p_win": 0.6536,
              "implied_odds": 1.53
            },
            {
              "sport": "nba",
              "match": "Los Angeles Lakers vs Orlando Magic",
              "pick": "Los Angeles Lakers",
              "p_win": 0.6103,
              "implied_odds": 1.64
            }
          ],
          "total_odds": 3.61,
          "combined_prob": 0.2777,
          "n_legs": 3
        },
        "cuota_6": {
          "legs": [
            {
              "sport": "nba",
              "match": "Chicago Bulls vs Charlotte Hornets",
              "pick": "Chicago Bulls",
              "p_win": 0.6961,
              "implied_odds": 1.44
            },
            {
              "sport": "nba",
              "match": "Milwaukee Bucks vs Miami Heat",
              "pick": "Milwaukee Bucks",
              "p_win": 0.6536,
              "implied_odds": 1.53
            },
            {
              "sport": "nba",
              "match": "Los Angeles Lakers vs Orlando Magic",
              "pick": "Los Angeles Lakers",
              "p_win": 0.6103,
              "implied_odds": 1.64
            }
          ],
          "total_odds": 3.61,
          "combined_prob": 0.2777,
          "n_legs": 3
        },
        "cuota_10": {
          "legs": [
            {
              "sport": "nba",
              "match": "Chicago Bulls vs Charlotte Hornets",
              "pick": "Chicago Bulls",
              "p_win": 0.6961,
              "implied_odds": 1.44
            },
            {
              "sport": "nba",
              "match": "Milwaukee Bucks vs Miami Heat",
              "pick": "Milwaukee Bucks",
              "p_win": 0.6536,
              "implied_odds": 1.53
            },
            {
              "sport": "nba",
              "match": "Los Angeles Lakers vs Orlando Magic",
              "pick": "Los Angeles Lakers",
              "p_win": 0.6103,
              "implied_odds": 1.64
            }
          ],
          "total_odds": 3.61,
          "combined_prob": 0.2777,
          "n_legs": 3
        },
        "cuota_20": {
          "legs": [
            {
              "sport": "nba",
              "match": "Chicago Bulls vs Charlotte Hornets",
              "pick": "Chicago Bulls",
              "p_win": 0.6961,
              "implied_odds": 1.44
            },
            {
              "sport": "nba",
              "match": "Milwaukee Bucks vs Miami Heat",
              "pick": "Milwaukee Bucks",
              "p_win": 0.6536,
              "implied_odds": 1.53
            },
            {
              "sport": "nba",
              "match": "Los Angeles Lakers vs Orlando Magic",
              "pick": "Los Angeles Lakers",
              "p_win": 0.6103,
              "implied_odds": 1.64
            }
          ],
          "total_odds": 3.61,
          "combined_prob": 0.2777,
          "n_legs": 3
        }
      }
    },
    "combined": {
      "cuota_3": {
        "legs": [
          {
            "sport": "nba",
            "match": "Milwaukee Bucks vs Miami Heat",
            "pick": "Milwaukee Bucks",
            "p_win": 0.6536,
            "implied_odds": 1.53
          },
          {
            "sport": "nba",
            "match": "Los Angeles Lakers vs Orlando Magic",
            "pick": "Los Angeles Lakers",
            "p_win": 0.6103,
            "implied_odds": 1.64
          }
        ],
        "total_odds": 2.51,
        "combined_prob": 0.3989,
        "n_legs": 2
      },
      "cuota_4": {
        "legs": [
          {
            "sport": "nba",
            "match": "Chicago Bulls vs Charlotte Hornets",
            "pick": "Chicago Bulls",
            "p_win": 0.6961,
            "implied_odds": 1.44
          },
          {
            "sport": "nba",
            "match": "Milwaukee Bucks vs Miami Heat",
            "pick": "Milwaukee Bucks",
            "p_win": 0.6536,
            "implied_odds": 1.53
          },
          {
            "sport": "nba",
            "match": "Los Angeles Lakers vs Orlando Magic",
            "pick": "Los Angeles Lakers",
            "p_win": 0.6103,
            "implied_odds": 1.64
          }
        ],
        "total_odds": 3.61,
        "combined_prob": 0.2777,
        "n_legs": 3
      },
      "cuota_5": {
        "legs": [
          {
            "sport": "nba",
            "match": "Chicago Bulls vs Charlotte Hornets",
            "pick": "Chicago Bulls",
            "p_win": 0.6961,
            "implied_odds": 1.44
          },
          {
            "sport": "nba",
            "match": "Milwaukee Bucks vs Miami Heat",
            "pick": "Milwaukee Bucks",
            "p_win": 0.6536,
            "implied_odds": 1.53
          },
          {
            "sport": "nba",
            "match": "Los Angeles Lakers vs Orlando Magic",
            "pick": "Los Angeles Lakers",
            "p_win": 0.6103,
            "implied_odds": 1.64
          }
        ],
        "total_odds": 3.61,
        "combined_prob": 0.2777,
        "n_legs": 3
      },
      "cuota_6": {
        "legs": [
          {
            "sport": "nba",
            "match": "Chicago Bulls vs Charlotte Hornets",
            "pick": "Chicago Bulls",
            "p_win": 0.6961,
            "implied_odds": 1.44
          },
          {
            "sport": "nba",
            "match": "Milwaukee Bucks vs Miami Heat",
            "pick": "Milwaukee Bucks",
            "p_win": 0.6536,
            "implied_odds": 1.53
          },
          {
            "sport": "nba",
            "match": "Los Angeles Lakers vs Orlando Magic",
            "pick": "Los Angeles Lakers",
            "p_win": 0.6103,
            "implied_odds": 1.64
          }
        ],
        "total_odds": 3.61,
        "combined_prob": 0.2777,
        "n_legs": 3
      },
      "cuota_10": {
        "legs": [
          {
            "sport": "nba",
            "match": "Chicago Bulls vs Charlotte Hornets",
            "pick": "Chicago Bulls",
            "p_win": 0.6961,
            "implied_odds": 1.44
          },
          {
            "sport": "nba",
            "match": "Milwaukee Bucks vs Miami Heat",
            "pick": "Milwaukee Bucks",
            "p_win": 0.6536,
            "implied_odds": 1.53
          },
          {
            "sport": "nba",
            "match": "Los Angeles Lakers vs Orlando Magic",
            "pick": "Los Angeles Lakers",
            "p_win": 0.6103,
            "implied_odds": 1.64
          }
        ],
        "total_odds": 3.61,
        "combined_prob": 0.2777,
        "n_legs": 3
      },
      "cuota_20": {
        "legs": [
          {
            "sport": "nba",
            "match": "Chicago Bulls vs Charlotte Hornets",
            "pick": "Chicago Bulls",
            "p_win": 0.6961,
            "implied_odds": 1.44
          },
          {
            "sport": "nba",
            "match": "Milwaukee Bucks vs Miami Heat",
            "pick": "Milwaukee Bucks",
            "p_win": 0.6536,
            "implied_odds": 1.53
          },
          {
            "sport": "nba",
            "match": "Los Angeles Lakers vs Orlando Magic",
            "pick": "Los Angeles Lakers",
            "p_win": 0.6103,
            "implied_odds": 1.64
          }
        ],
        "total_odds": 3.61,
        "combined_prob": 0.2777,
        "n_legs": 3
      }
    }
  }
}