{
  "generated_at": "2026-07-12T09:50:41Z",
  "date": "2026-07-12",
  "sports": {
    "nba": {
      "status": "ok",
      "metrics": {
        "accuracy": 0.65,
        "logloss": 0.621,
        "brier": 0.2152
      },
      "picks": [],
      "name": "NBA"
    },
    "nhl": {
      "status": "ok",
      "metrics": {
        "accuracy": 0.5189,
        "logloss": 0.6924,
        "brier": 0.2496
      },
      "picks": [],
      "name": "NHL"
    },
    "mlb": {
      "status": "ok",
      "metrics": {
        "accuracy": 0.5245,
        "logloss": 0.6916,
        "brier": 0.2492
      },
      "picks": [
        {
          "home_team": "Chicago White Sox",
          "away_team": "Athletics",
          "pick": "H",
          "pick_label": "Chicago White Sox",
          "p_win": 0.5954,
          "implied_odds": 1.68,
          "signal": "media",
          "date": "2026-07-12",
          "model_spread": 0.7,
          "house_spread": null,
          "house_odds": null,
          "house_implied_pct": null,
          "edge_pct": null,
          "house_total": null,
          "espn_ou": null,
          "ou_line": null,
          "ou_pick": null,
          "pts_home_scored": null,
          "pts_home_allowed": null,
          "pts_away_scored": null,
          "pts_away_allowed": null,
          "injuries_home": [],
          "injuries_away": [],
          "note": "⚠️ Modelo 60%. Sox 49-45 vs Athletics 41-54. Sin bajas importantes. ML Sox con cautela (modelo 60%)."
        },
        {
          "home_team": "Baltimore Orioles",
          "away_team": "Kansas City Royals",
          "pick": "H",
          "pick_label": "Baltimore Orioles",
          "p_win": 0.5524,
          "implied_odds": 1.81,
          "signal": "baja",
          "date": "2026-07-12",
          "model_spread": 0.4,
          "house_spread": null,
          "house_odds": null,
          "house_implied_pct": null,
          "edge_pct": null,
          "house_total": null,
          "espn_ou": null,
          "ou_line": null,
          "ou_pick": null,
          "pts_home_scored": null,
          "pts_home_allowed": null,
          "pts_away_scored": null,
          "pts_away_allowed": null,
          "injuries_home": [],
          "injuries_away": [],
          "note": "❌ Modelo 55%. Orioles 45-51 vs Royals 38-58. Sin bajas importantes. SKIP — sin edge claro (55%)."
        },
        {
          "home_team": "Tampa Bay Rays",
          "away_team": "Seattle Mariners",
          "pick": "H",
          "pick_label": "Tampa Bay Rays",
          "p_win": 0.551,
          "implied_odds": 1.81,
          "signal": "baja",
          "date": "2026-07-12",
          "model_spread": 0.4,
          "house_spread": null,
          "house_odds": null,
          "house_implied_pct": null,
          "edge_pct": null,
          "house_total": null,
          "espn_ou": null,
          "ou_line": null,
          "ou_pick": null,
          "pts_home_scored": null,
          "pts_home_allowed": null,
          "pts_away_scored": null,
          "pts_away_allowed": null,
          "injuries_home": [],
          "injuries_away": [],
          "note": "❌ Modelo 55%. Rays 56-37 vs Mariners 47-49. Sin bajas importantes. SKIP — sin edge claro (55%)."
        }
      ],
      "name": "MLB",
      "analysis": ""
    },
    "epl": {
      "status": "ok",
      "metrics": {
        "accuracy": 0.4605,
        "logloss": 1.079,
        "brier": 0.2184
      },
      "picks": [],
      "name": "Premier League"
    },
    "laliga": {
      "status": "ok",
      "metrics": {
        "accuracy": 0.4737,
        "logloss": 1.0286,
        "brier": 0.206
      },
      "picks": [],
      "name": "La Liga"
    },
    "ligue1": {
      "status": "ok",
      "metrics": {
        "accuracy": 0.623,
        "logloss": 0.918,
        "brier": 0.1827
      },
      "picks": [],
      "name": "Ligue 1"
    },
    "bundesliga": {
      "status": "ok",
      "metrics": {
        "accuracy": 0.4839,
        "logloss": 0.9812,
        "brier": 0.195
      },
      "picks": [],
      "name": "Bundesliga"
    },
    "primeira": {
      "status": "ok",
      "metrics": {
        "accuracy": 0.5484,
        "logloss": 0.998,
        "brier": 0.1974
      },
      "picks": [],
      "name": "Primeira Liga"
    },
    "ucl": {
      "status": "ok",
      "metrics": {
        "accuracy": 0.5263,
        "logloss": 1.0295,
        "brier": 0.2073
      },
      "picks": [],
      "name": "Champions League"
    }
  },
  "parlays": {
    "by_sport": {
      "mlb": {
        "cuota_3": {
          "legs": [
            {
              "sport": "mlb",
              "match": "Chicago White Sox vs Athletics",
              "pick": "Chicago White Sox",
              "p_win": 0.5954,
              "implied_odds": 1.68
            },
            {
              "sport": "mlb",
              "match": "Baltimore Orioles vs Kansas City Royals",
              "pick": "Baltimore Orioles",
              "p_win": 0.5524,
              "implied_odds": 1.81
            }
          ],
          "total_odds": 3.04,
          "combined_prob": 0.3289,
          "n_legs": 2
        },
        "cuota_4": {
          "legs": [
            {
              "sport": "mlb",
              "match": "Baltimore Orioles vs Kansas City Royals",
              "pick": "Baltimore Orioles",
              "p_win": 0.5524,
              "implied_odds": 1.81
            },
            {
              "sport": "mlb",
              "match": "Tampa Bay Rays vs Seattle Mariners",
              "pick": "Tampa Bay Rays",
              "p_win": 0.551,
              "implied_odds": 1.81
            }
          ],
          "total_odds": 3.28,
          "combined_prob": 0.3044,
          "n_legs": 2
        },
        "cuota_5": {
          "legs": [
            {
              "sport": "mlb",
              "match": "Chicago White Sox vs Athletics",
              "pick": "Chicago White Sox",
              "p_win": 0.5954,
              "implied_odds": 1.68
            },
            {
              "sport": "mlb",
              "match": "Baltimore Orioles vs Kansas City Royals",
              "pick": "Baltimore Orioles",
              "p_win": 0.5524,
              "implied_odds": 1.81
            },
            {
              "sport": "mlb",
              "match": "Tampa Bay Rays vs Seattle Mariners",
              "pick": "Tampa Bay Rays",
              "p_win": 0.551,
              "implied_odds": 1.81
            }
          ],
          "total_odds": 5.5,
          "combined_prob": 0.1812,
          "n_legs": 3
        },
        "cuota_6": {
          "legs": [
            {
              "sport": "mlb",
              "match": "Chicago White Sox vs Athletics",
              "pick": "Chicago White Sox",
              "p_win": 0.5954,
              "implied_odds": 1.68
            },
            {
              "sport": "mlb",
              "match": "Baltimore Orioles vs Kansas City Royals",
              "pick": "Baltimore Orioles",
              "p_win": 0.5524,
              "implied_odds": 1.81
            },
            {
              "sport": "mlb",
              "match": "Tampa Bay Rays vs Seattle Mariners",
              "pick": "Tampa Bay Rays",
              "p_win": 0.551,
              "implied_odds": 1.81
            }
          ],
          "total_odds": 5.5,
          "combined_prob": 0.1812,
          "n_legs": 3
        },
        "cuota_10": {
          "legs": [
            {
              "sport": "mlb",
              "match": "Chicago White Sox vs Athletics",
              "pick": "Chicago White Sox",
              "p_win": 0.5954,
              "implied_odds": 1.68
            },
            {
              "sport": "mlb",
              "match": "Baltimore Orioles vs Kansas City Royals",
              "pick": "Baltimore Orioles",
              "p_win": 0.5524,
              "implied_odds": 1.81
            },
            {
              "sport": "mlb",
              "match": "Tampa Bay Rays vs Seattle Mariners",
              "pick": "Tampa Bay Rays",
              "p_win": 0.551,
              "implied_odds": 1.81
            }
          ],
          "total_odds": 5.5,
          "combined_prob": 0.1812,
          "n_legs": 3
        },
        "cuota_20": {
          "legs": [
            {
              "sport": "mlb",
              "match": "Chicago White Sox vs Athletics",
              "pick": "Chicago White Sox",
              "p_win": 0.5954,
              "implied_odds": 1.68
            },
            {
              "sport": "mlb",
              "match": "Baltimore Orioles vs Kansas City Royals",
              "pick": "Baltimore Orioles",
              "p_win": 0.5524,
              "implied_odds": 1.81
            },
            {
              "sport": "mlb",
              "match": "Tampa Bay Rays vs Seattle Mariners",
              "pick": "Tampa Bay Rays",
              "p_win": 0.551,
              "implied_odds": 1.81
            }
          ],
          "total_odds": 5.5,
          "combined_prob": 0.1812,
          "n_legs": 3
        }
      }
    },
    "combined": {
      "cuota_3": {
        "legs": [
          {
            "sport": "mlb",
            "match": "Chicago White Sox vs Athletics",
            "pick": "Chicago White Sox",
            "p_win": 0.5954,
            "implied_odds": 1.68
          },
          {
            "sport": "mlb",
            "match": "Baltimore Orioles vs Kansas City Royals",
            "pick": "Baltimore Orioles",
            "p_win": 0.5524,
            "implied_odds": 1.81
          }
        ],
        "total_odds": 3.04,
        "combined_prob": 0.3289,
        "n_legs": 2
      },
      "cuota_4": {
        "legs": [
          {
            "sport": "mlb",
            "match": "Baltimore Orioles vs Kansas City Royals",
            "pick": "Baltimore Orioles",
            "p_win": 0.5524,
            "implied_odds": 1.81
          },
          {
            "sport": "mlb",
            "match": "Tampa Bay Rays vs Seattle Mariners",
            "pick": "Tampa Bay Rays",
            "p_win": 0.551,
            "implied_odds": 1.81
          }
        ],
        "total_odds": 3.28,
        "combined_prob": 0.3044,
        "n_legs": 2
      },
      "cuota_5": {
        "legs": [
          {
            "sport": "mlb",
            "match": "Chicago White Sox vs Athletics",
            "pick": "Chicago White Sox",
            "p_win": 0.5954,
            "implied_odds": 1.68
          },
          {
            "sport": "mlb",
            "match": "Baltimore Orioles vs Kansas City Royals",
            "pick": "Baltimore Orioles",
            "p_win": 0.5524,
            "implied_odds": 1.81
          },
          {
            "sport": "mlb",
            "match": "Tampa Bay Rays vs Seattle Mariners",
            "pick": "Tampa Bay Rays",
            "p_win": 0.551,
            "implied_odds": 1.81
          }
        ],
        "total_odds": 5.5,
        "combined_prob": 0.1812,
        "n_legs": 3
      },
      "cuota_6": {
        "legs": [
          {
            "sport": "mlb",
            "match": "Chicago White Sox vs Athletics",
            "pick": "Chicago White Sox",
            "p_win": 0.5954,
            "implied_odds": 1.68
          },
          {
            "sport": "mlb",
            "match": "Baltimore Orioles vs Kansas City Royals",
            "pick": "Baltimore Orioles",
            "p_win": 0.5524,
            "implied_odds": 1.81
          },
          {
            "sport": "mlb",
            "match": "Tampa Bay Rays vs Seattle Mariners",
            "pick": "Tampa Bay Rays",
            "p_win": 0.551,
            "implied_odds": 1.81
          }
        ],
        "total_odds": 5.5,
        "combined_prob": 0.1812,
        "n_legs": 3
      },
      "cuota_10": {
        "legs": [
          {
            "sport": "mlb",
            "match": "Chicago White Sox vs Athletics",
            "pick": "Chicago White Sox",
            "p_win": 0.5954,
            "implied_odds": 1.68
          },
          {
            "sport": "mlb",
            "match": "Baltimore Orioles vs Kansas City Royals",
            "pick": "Baltimore Orioles",
            "p_win": 0.5524,
            "implied_odds": 1.81
          },
          {
            "sport": "mlb",
            "match": "Tampa Bay Rays vs Seattle Mariners",
            "pick": "Tampa Bay Rays",
            "p_win": 0.551,
            "implied_odds": 1.81
          }
        ],
        "total_odds": 5.5,
        "combined_prob": 0.1812,
        "n_legs": 3
      },
      "cuota_20": {
        "legs": [
          {
            "sport": "mlb",
            "match": "Chicago White Sox vs Athletics",
            "pick": "Chicago White Sox",
            "p_win": 0.5954,
            "implied_odds": 1.68
          },
          {
            "sport": "mlb",
            "match": "Baltimore Orioles vs Kansas City Royals",
            "pick": "Baltimore Orioles",
            "p_win": 0.5524,
            "implied_odds": 1.81
          },
          {
            "sport": "mlb",
            "match": "Tampa Bay Rays vs Seattle Mariners",
            "pick": "Tampa Bay Rays",
            "p_win": 0.551,
            "implied_odds": 1.81
          }
        ],
        "total_odds": 5.5,
        "combined_prob": 0.1812,
        "n_legs": 3
      }
    }
  }
}